Metadata-Version: 2.1
Name: mediaclass-whisper
Version: 20231117
Summary: Robust Speech Recognition via Large-Scale Weak Supervision
Home-page: https://github.com/PalatineVision/mediaclass_whisper
Author: OpenAI
License: MIT
Requires-Python: >=3.8
License-File: LICENSE
Requires-Dist: numba
Requires-Dist: numpy
Requires-Dist: torch
Requires-Dist: tqdm
Requires-Dist: more-itertools
Requires-Dist: tiktoken
Requires-Dist: triton<3,>=2.0.0; platform_machine == "x86_64" and sys_platform == "linux" or sys_platform == "linux2"
Provides-Extra: dev
Requires-Dist: pytest; extra == "dev"
Requires-Dist: scipy; extra == "dev"
Requires-Dist: black; extra == "dev"
Requires-Dist: flake8; extra == "dev"
Requires-Dist: isort; extra == "dev"
